[
  {
    "anonymous":false,
    "inputs":[
      {
        "indexed":false,
        "internalType":"bytes32",
        "name":"name",
        "type":"bytes32"
      },
      {
        "indexed":false,
        "internalType":"bytes",
        "name":"data",
        "type":"bytes"
      }
    ],
    "name":"Ethernize",
    "type":"event"
  },
  {
    "stateMutability":"nonpayable",
    "type":"fallback"
  },
  {
    "inputs":[
      {
        "internalType":"bytes32",
        "name":"name",
        "type":"bytes32"
      },
      {
        "internalType":"bytes",
        "name":"data",
        "type":"bytes"
      }
    ],
    "name":"ethernize",
    "outputs":[],
    "stateMutability":"nonpayable",
    "type":"function"
  }
]